setup.py
wlwx/Config.py
wlwx/HttpUtil.py
wlwx/MultiSmsOperator.py
wlwx/Result.py
wlwx/SmsOperator.py
wlwx/__init__.py
wlwx_python_sdk.egg-info/PKG-INFO
wlwx_python_sdk.egg-info/SOURCES.txt
wlwx_python_sdk.egg-info/dependency_links.txt
wlwx_python_sdk.egg-info/requires.txt
wlwx_python_sdk.egg-info/top_level.txt