Metadata-Version: 1.0
Name: wlwx-python-sdk
Version: 0.0.5
Summary: The http://www.10690757.com python sdk.
Home-page: http://www.10690757.com
Author: zhouzhao
Author-email: 2880987282@qq.com
License: MIT License
Keywords: wlwx,sdk,python
Platform: any
